{
  "type": "FeatureCollection",
  "features": [
    {
      "type": "Feature",
      "properties": {
          "name": "Helados Bon (Av. Gregorio Rivas (La Sirena), La Vega)",
          "amenity": "",
          "popupContent": ""
      },
      "geometry": {
          "type": "Point",
          "coordinates": [19.225592742630106, -70.51694783944626]
      }
    },
    {
      "type": "Feature",
      "properties": {
          "name": "Helados Bon - Yogen Früz (Av. Pedro A. Rivera (Jumbo), La Vega)",
          "amenity": "",
          "popupContent": ""
      },
      "geometry": {
          "type": "Point",
          "coordinates": [19.224524013752706, -70.52145629321629]
      }
    },
    {
      "type": "Feature",
      "properties": {
          "name": "Helados Bon - Yogen Früz (Av. Imbert, La Vega)",
          "amenity": "",
          "popupContent": ""
      },
      "geometry": {
          "type": "Point",
          "coordinates": [19.219883040430712, -70.52761558203952]
      }
    },
    {
      "type": "Feature",
      "properties": {
          "name": "Helados Bon - Yogen Früz (Calle Don Antonio Guzmán, La Vega)",
          "amenity": "",
          "popupContent": ""
      },
      "geometry": {
          "type": "Point",
          "coordinates": [19.22405671797822, -70.53233002918226]
      }
    }
  ]
}
