{
  "type": "FeatureCollection",
  "features": [
    {
      "type": "Feature",
      "properties": {
          "name": "Helados Bon (Río San Juan)",
          "amenity": "",
          "popupContent": ""
      },
      "geometry": {
          "type": "Point",
          "coordinates": [19.6442504274122, -70.07528680676263]
      }
    }
  ]
}
